{
    "Ar36": {
        "error": 0.0007513783166541392,
        "error_type": "SEM",
        "filter_outliers_dict": {
            "filter_outliers": true,
            "iterations": 1,
            "std_devs": 3,
            "use_iqr_filtering": false,
            "use_standard_deviation_filtering": false
        },
        "fit": "linear",
        "fn": 29,
        "include_baseline_error": true,
        "n": 29,
        "outlier_excluded": [],
        "reviewed": true,
        "user_excluded": [],
        "value": 0.0065152856921995815
    },
    "Ar37": {
        "error": 0.01940895969734038,
        "error_type": "SEM",
        "filter_outliers_dict": {
            "filter_outliers": true,
            "iterations": 1,
            "std_devs": 3,
            "use_iqr_filtering": false,
            "use_standard_deviation_filtering": false
        },
        "fit": "linear",
        "fn": 29,
        "include_baseline_error": true,
        "n": 29,
        "outlier_excluded": [],
        "reviewed": true,
        "user_excluded": [],
        "value": -0.04491343390779841
    },
    "Ar38": {
        "error": 0.020209251959461026,
        "error_type": "SEM",
        "filter_outliers_dict": {
            "filter_outliers": true,
            "iterations": 1,
            "std_devs": 3,
            "use_iqr_filtering": false,
            "use_standard_deviation_filtering": false
        },
        "fit": "linear",
        "fn": 29,
        "include_baseline_error": true,
        "n": 29,
        "outlier_excluded": [],
        "reviewed": true,
        "user_excluded": [],
        "value": 0.0400166663358573
    },
    "Ar39": {
        "error": 0.03704833192187737,
        "error_type": "SEM",
        "filter_outliers_dict": {
            "filter_outliers": true,
            "iterations": 1,
            "std_devs": 3,
            "use_iqr_filtering": false,
            "use_standard_deviation_filtering": false
        },
        "fit": "linear",
        "fn": 29,
        "include_baseline_error": true,
        "n": 29,
        "outlier_excluded": [],
        "reviewed": true,
        "user_excluded": [],
        "value": -0.016445693129707287
    },
    "Ar40": {
        "error": 0.046749363386263905,
        "error_type": "SEM",
        "filter_outliers_dict": {
            "filter_outliers": true,
            "iterations": 1,
            "std_devs": 3,
            "use_iqr_filtering": false,
            "use_standard_deviation_filtering": false
        },
        "fit": "linear",
        "fn": 29,
        "include_baseline_error": true,
        "n": 29,
        "outlier_excluded": [],
        "reviewed": true,
        "user_excluded": [],
        "value": 24.844090026356337
    },
    "Ar41": {
        "error": 0.15629393437008834,
        "error_type": "SEM",
        "filter_outliers_dict": {
            "filter_outliers": true,
            "iterations": 1,
            "std_devs": 2
        },
        "fit": "linear",
        "value": -0.27167095117695855
    }
}