{
    "AX": {
        "error": 0.0116413293238871,
        "error_type": "SEM",
        "filter_outliers_dict": {
            "filter_outliers": true,
            "iterations": 1,
            "std_devs": 3,
            "use_iqr_filtering": false,
            "use_standard_deviation_filtering": false
        },
        "fit": "average",
        "fn": 29,
        "include_baseline_error": false,
        "n": 29,
        "outlier_excluded": [],
        "reviewed": true,
        "user_excluded": [],
        "value": 0.025385347869375657
    },
    "CDD": {
        "error": 5.289331652577324e-06,
        "error_type": "SEM",
        "filter_outliers_dict": {
            "filter_outliers": true,
            "iterations": 1,
            "std_devs": 10,
            "use_iqr_filtering": false,
            "use_standard_deviation_filtering": false
        },
        "fit": "average",
        "fn": 29,
        "include_baseline_error": false,
        "n": 29,
        "outlier_excluded": [],
        "reviewed": true,
        "user_excluded": [],
        "value": 5.2893316525773245e-06
    },
    "H1": {
        "error": 0.008579797968279226,
        "error_type": "SEM",
        "filter_outliers_dict": {
            "filter_outliers": true,
            "iterations": 1,
            "std_devs": 3,
            "use_iqr_filtering": false,
            "use_standard_deviation_filtering": false
        },
        "fit": "average",
        "fn": 29,
        "include_baseline_error": false,
        "n": 29,
        "outlier_excluded": [],
        "reviewed": true,
        "user_excluded": [],
        "value": 0.0406207650024765
    },
    "H2": {
        "error": 0.053004205967129916,
        "error_type": "SEM",
        "filter_outliers_dict": {
            "filter_outliers": true,
            "iterations": 1,
            "std_devs": 3,
            "use_iqr_filtering": false,
            "use_standard_deviation_filtering": false
        },
        "fit": "average",
        "fn": 29,
        "include_baseline_error": false,
        "n": 29,
        "outlier_excluded": [],
        "reviewed": true,
        "user_excluded": [],
        "value": -0.2789858747875832
    },
    "L1": {
        "error": 0.004088194877069299,
        "error_type": "SEM",
        "filter_outliers_dict": {
            "filter_outliers": true,
            "iterations": 1,
            "std_devs": 3,
            "use_iqr_filtering": false,
            "use_standard_deviation_filtering": false
        },
        "fit": "average",
        "fn": 29,
        "include_baseline_error": false,
        "n": 29,
        "outlier_excluded": [],
        "reviewed": true,
        "user_excluded": [],
        "value": 0.02459273356061172
    },
    "L2": {
        "error": 0.004843795626115289,
        "error_type": "SEM",
        "filter_outliers_dict": {
            "filter_outliers": true,
            "iterations": 1,
            "std_devs": 2
        },
        "fit": "average",
        "value": -0.044686078115773666
    }
}