{
    "AX": {
        "error": 0.007239883299916983,
        "error_type": null,
        "filter_outliers_dict": {
            "filter_outliers": true,
            "iterations": 1,
            "std_devs": 2,
            "use_iqr_filtering": false,
            "use_standard_deviation_filtering": false
        },
        "fit": "average",
        "fn": 0,
        "include_baseline_error": false,
        "n": 0,
        "outlier_excluded": null,
        "reviewed": false,
        "user_excluded": null,
        "value": 0.06264983264701406
    },
    "CDD": {
        "error": 9.937925824488048e-06,
        "error_type": null,
        "filter_outliers_dict": {
            "filter_outliers": true,
            "iterations": 1,
            "std_devs": 10,
            "use_iqr_filtering": false,
            "use_standard_deviation_filtering": false
        },
        "fit": "average",
        "fn": 0,
        "include_baseline_error": false,
        "n": 0,
        "outlier_excluded": null,
        "reviewed": false,
        "user_excluded": null,
        "value": 3.7495483333801055e-05
    },
    "H1": {
        "error": 0.007250550203025341,
        "error_type": null,
        "filter_outliers_dict": {
            "filter_outliers": true,
            "iterations": 1,
            "std_devs": 2,
            "use_iqr_filtering": false,
            "use_standard_deviation_filtering": false
        },
        "fit": "average",
        "fn": 0,
        "include_baseline_error": false,
        "n": 0,
        "outlier_excluded": null,
        "reviewed": false,
        "user_excluded": null,
        "value": 0.045300834416731384
    },
    "H2": {
        "error": 0.04394489526748657,
        "error_type": null,
        "filter_outliers_dict": {
            "filter_outliers": true,
            "iterations": 1,
            "std_devs": 2,
            "use_iqr_filtering": false,
            "use_standard_deviation_filtering": false
        },
        "fit": "average",
        "fn": 0,
        "include_baseline_error": false,
        "n": 0,
        "outlier_excluded": null,
        "reviewed": false,
        "user_excluded": null,
        "value": -0.330748289421287
    },
    "L1": {
        "error": 0.0036624374333769083,
        "error_type": null,
        "filter_outliers_dict": {
            "filter_outliers": true,
            "iterations": 1,
            "std_devs": 2,
            "use_iqr_filtering": false,
            "use_standard_deviation_filtering": false
        },
        "fit": "average",
        "fn": 0,
        "include_baseline_error": false,
        "n": 0,
        "outlier_excluded": null,
        "reviewed": false,
        "user_excluded": null,
        "value": 0.02911379819961532
    },
    "L2": {
        "error": 0.002995293354615569,
        "error_type": null,
        "filter_outliers_dict": {
            "filter_outliers": true,
            "iterations": 1,
            "std_devs": 2,
            "use_iqr_filtering": false,
            "use_standard_deviation_filtering": false
        },
        "fit": "average",
        "fn": 0,
        "include_baseline_error": false,
        "n": 0,
        "outlier_excluded": null,
        "reviewed": false,
        "user_excluded": null,
        "value": -0.04162611701892081
    }
}